{
  "episodes": [
    {
      "title": "Episode 1",
      "url": "https://pixeldrain.com/api/file/b4aQxgoD"
    },
    {
      "title": "Episode 2",
      "url": "https://pixeldrain.com/api/file/Lbgt2RS2"
    },
    {
      "title": "Episode 3",
      "url": "https://pixeldrain.com/api/file/59Jbn8xJ"
    },
    {
      "title": "Episode 4",
      "url": "https://pixeldrain.com/api/file/ejcXfQNJ"
    },
    {
      "title": "Episode 5",
      "url": "https://pixeldrain.com/api/file/msX4yBKM"
    },
    {
      "title": "Episode 6",
      "url": "https://pixeldrain.com/api/file/soGZy98Z"
    },
    {
      "title": "Episode 7",
      "url": "https://pixeldrain.com/api/file/3MSbkBpc"
    }
  ]
}
